zbMcLib/__init__.py
zbMcLib/mccn/__init__.py
zbMcLib/mccn/bplist.py
zbMcLib/mccn/ccui.py
zbMcLib/mccn/h5api.py
zbMcLib/mccn/home.py
zbMcLib/mccn/name.py
zbMcLib/mccn/url.py
zbMcLib/mccn/version.py
zbmclib-0.2.20.dist-info/licenses/LICENSE
zbmclib-0.2.20.dist-info/METADATA
zbmclib-0.2.20.dist-info/WHEEL
zbmclib-0.2.20.dist-info/top_level.txt
zbmclib-0.2.20.dist-info/RECORD
