Metadata-Version: 2.4
Name: zbMcLib
Version: 0.2.20
Summary: zbMinecraft库
Author-email: Ianzb <93322252@qq.com>
Maintainer-email: Ianzb <93322252@qq.com>
License: MIT License
Project-URL: Repository, https://github.com/Ianzb/zbMcLib/
Keywords: zb,Ianzb,Minecraft,lib
Classifier: Programming Language :: Python :: 3
Classifier: Programming Language :: Python :: 3.13
Classifier: License :: OSI Approved :: MIT License
Classifier: Operating System :: OS Independent
Classifier: Operating System :: Microsoft :: Windows
Classifier: Operating System :: MacOS :: MacOS X
Classifier: Operating System :: POSIX :: Linux
Requires-Python: >=3.12
License-File: LICENSE
Requires-Dist: zbToolLib>=2.0.7
Requires-Dist: lxml>=6.0.2
Requires-Dist: beautifulsoup4>=4.14.3
Requires-Dist: pillow>=12.0.0
Dynamic: license-file
